MANIFEST.in
README.rst
setup.py
mo2s3/__init__.py
mo2s3/core.py
mo2s3.egg-info/PKG-INFO
mo2s3.egg-info/SOURCES.txt
mo2s3.egg-info/dependency_links.txt
mo2s3.egg-info/entry_points.txt
mo2s3.egg-info/requires.txt
mo2s3.egg-info/top_level.txt