Metadata-Version: 1.1
Name: mo2s3
Version: 0.0.1
Summary: A python command line tool that simplify MongoDB backup (mongodump/mongorestore) to Amazon S3.
Home-page: http://pypi.python.org/pypi/mo2s3
Author: Thomas Sileo
Author-email: thomas.sileo@gmail.com
License: MIT
Keywords: aws s3 mongodb backup restore archive
Platform: UNKNOWN
Classifier: Development Status :: 4 - Beta
Classifier: Topic :: System :: Archiving :: Backup
Classifier: License :: OSI Approved :: MIT License
